gurux_serial/GXSerial.py
gurux_serial/_GXSynchronousMediaBase.py
gurux_serial/__init__.py
gurux_serial/_handlers/GXLinuxHandler.py
gurux_serial/_handlers/GXSettings.py
gurux_serial/_handlers/GXWindowsHandler.py
gurux_serial/_handlers/IGXNative.py
gurux_serial/_handlers/__init__.py
gurux_serial-1.0.21.dist-info/LICENSE
gurux_serial-1.0.21.dist-info/METADATA
gurux_serial-1.0.21.dist-info/WHEEL
gurux_serial-1.0.21.dist-info/top_level.txt
gurux_serial-1.0.21.dist-info/RECORD
